uvp_adb
