Metadata-Version: 1.1
Name: uvp-adb
Version: 2.1
Summary: adb functions for uvp phone
Home-page: https://github.com/inforfang/uvp_adb
Author: inforfang
Author-email: szaforward2@gmail.com
License: MIT
Download-URL: https://github.com/inforfang/uvp_adb/tarball/2.01
Platform: UNKNOWN
